{
    "columns":[
        "scholar_id",
        "name",
        "affiliation",
        "email_domain",
        "url_picture",
        "citedby",
        "interests",
        "citedby5y",
        "hindex",
        "hindex5y",
        "i10index",
        "i10index5y",
        "coauthors"
    ],
    "index":[
        0
    ],
    "data":[
        [
            "5XnK14gAAAAJ",
            "David Arthur Hsieh",
            "Professor of Finance, Fuqual School of Business, Duke University",
            "@duke.edu",
            "https:\/\/scholar.google.com\/citations?view_op=medium_photo&user=5XnK14gAAAAJ",
            17551,
            [
                "Economics",
                "Econometrics",
                "Finance",
                "Statistics"
            ],
            3175,
            46,
            26,
            55,
            40,
            [
                {
                    "container_type":"Author",
                    "filled":[

                    ],
                    "scholar_id":"tKPbPFUAAAAJ",
                    "source":{
                        "name":"CO_AUTHORS_LIST"
                    },
                    "name":"william brock",
                    "affiliation":"professor of economics, university of wisconsin, madison"
                },
                {
                    "container_type":"Author",
                    "filled":[

                    ],
                    "scholar_id":"CiwEc6gAAAAJ",
                    "source":{
                        "name":"CO_AUTHORS_LIST"
                    },
                    "name":"Blake LeBaron",
                    "affiliation":"International Business School, Brandeis University"
                },
                {
                    "container_type":"Author",
                    "filled":[

                    ],
                    "scholar_id":"TQ0uLf8AAAAJ",
                    "source":{
                        "name":"CO_AUTHORS_LIST"
                    },
                    "name":"Tarun Ramadorai",
                    "affiliation":"Professor of Financial Economics, Imperial College London"
                },
                {
                    "container_type":"Author",
                    "filled":[

                    ],
                    "scholar_id":"qnCATE8AAAAJ",
                    "source":{
                        "name":"CO_AUTHORS_LIST"
                    },
                    "name":"A. Ronald Gallant",
                    "affiliation":"Professor of Economics, Penn State University"
                },
                {
                    "container_type":"Author",
                    "filled":[

                    ],
                    "scholar_id":"3T-bhxwwQU8C",
                    "source":{
                        "name":"CO_AUTHORS_LIST"
                    },
                    "name":"George Tauchen",
                    "affiliation":"Professor of Economics"
                },
                {
                    "container_type":"Author",
                    "filled":[

                    ],
                    "scholar_id":"wAwboAcAAAAJ",
                    "source":{
                        "name":"CO_AUTHORS_LIST"
                    },
                    "name":"Charles F. Manski",
                    "affiliation":"Northwestern University"
                },
                {
                    "container_type":"Author",
                    "filled":[

                    ],
                    "scholar_id":"Bz-VsLwAAAAJ",
                    "source":{
                        "name":"CO_AUTHORS_LIST"
                    },
                    "name":"S Viswanathan",
                    "affiliation":"Professor of Finance, Duke University"
                },
                {
                    "container_type":"Author",
                    "filled":[

                    ],
                    "scholar_id":"GVRWVbAAAAAJ",
                    "source":{
                        "name":"CO_AUTHORS_LIST"
                    },
                    "name":"Nalin Kulatilaka",
                    "affiliation":"Boston University"
                },
                {
                    "container_type":"Author",
                    "filled":[

                    ],
                    "scholar_id":"1dx5Y-kAAAAJ",
                    "source":{
                        "name":"CO_AUTHORS_LIST"
                    },
                    "name":"Melvyn Teo",
                    "affiliation":"Lee Kong Chian Professor of Finance, Singapore Management University"
                },
                {
                    "container_type":"Author",
                    "filled":[

                    ],
                    "scholar_id":"BnjVZroAAAAJ",
                    "source":{
                        "name":"CO_AUTHORS_LIST"
                    },
                    "name":"John Bilson",
                    "affiliation":"Dean and Professor of Finance, Illinois Institute of Technology"
                }
            ]
        ]
    ]
}