{
    "columns":[
        "scholar_id",
        "name",
        "affiliation",
        "email_domain",
        "url_picture",
        "citedby",
        "interests",
        "citedby5y",
        "hindex",
        "hindex5y",
        "i10index",
        "i10index5y",
        "coauthors"
    ],
    "index":[
        0
    ],
    "data":[
        [
            "7L58djQAAAAJ",
            "Olga Korotkova",
            "Professor of Physics, University of Miami",
            "@physics.miami.edu",
            "https:\/\/scholar.google.com\/citations?view_op=medium_photo&user=7L58djQAAAAJ",
            8826,
            [
                "Optics",
                "Optical Turbulence",
                "Atmospheric optics",
                "Ocean optics"
            ],
            4330,
            53,
            35,
            153,
            115,
            [
                {
                    "container_type":"Author",
                    "filled":[

                    ],
                    "scholar_id":"v3zNSbIAAAAJ",
                    "source":{
                        "name":"CO_AUTHORS_LIST"
                    },
                    "name":"Prof.Yangjian Cai (\u8521\u9633\u5065)",
                    "affiliation":"Soochow University & Shandong Normal University, China"
                },
                {
                    "container_type":"Author",
                    "filled":[

                    ],
                    "scholar_id":"K_E7rYYAAAAJ",
                    "source":{
                        "name":"CO_AUTHORS_LIST"
                    },
                    "name":"\u0415\u043b\u0435\u043d\u0430 \u0410\u043d\u0430\u0442\u043e\u043b\u044c\u0435\u0432\u043d\u0430 \u0429\u0435\u043f\u0430\u043a\u0438\u043d\u0430 (Elen...",
                    "affiliation":"\u0421\u0430\u043c\u0430\u0440\u0441\u043a\u0438\u0439 \u0443\u043d\u0438\u0432\u0435\u0440\u0441\u0438\u0442\u0435\u0442 (Samara University)"
                },
                {
                    "container_type":"Author",
                    "filled":[

                    ],
                    "scholar_id":"wXqpohUAAAAJ",
                    "source":{
                        "name":"CO_AUTHORS_LIST"
                    },
                    "name":"Zhisong Tong",
                    "affiliation":"Nilogen Oncosystems"
                },
                {
                    "container_type":"Author",
                    "filled":[

                    ],
                    "scholar_id":"dLX8b-oAAAAJ",
                    "source":{
                        "name":"CO_AUTHORS_LIST"
                    },
                    "name":"Yahya Baykal",
                    "affiliation":"\u00c7ankaya University"
                },
                {
                    "container_type":"Author",
                    "filled":[

                    ],
                    "scholar_id":"6EMmL2kAAAAJ",
                    "source":{
                        "name":"CO_AUTHORS_LIST"
                    },
                    "name":"Dr. Italo Toselli",
                    "affiliation":"Fraunhofer IOSB"
                },
                {
                    "container_type":"Author",
                    "filled":[

                    ],
                    "scholar_id":"hhXOeP4AAAAJ",
                    "source":{
                        "name":"CO_AUTHORS_LIST"
                    },
                    "name":"Svetlana Avramov-Zamurovic",
                    "affiliation":"Professor US Naval Academy"
                },
                {
                    "container_type":"Author",
                    "filled":[

                    ],
                    "scholar_id":"aLDxx9UAAAAJ",
                    "source":{
                        "name":"CO_AUTHORS_LIST"
                    },
                    "name":"Greg Gbur",
                    "affiliation":"University of North Carolina at Charlotte, Physics and Optical Science"
                },
                {
                    "container_type":"Author",
                    "filled":[

                    ],
                    "scholar_id":"P9lUbisAAAAJ",
                    "source":{
                        "name":"CO_AUTHORS_LIST"
                    },
                    "name":"Jia Li",
                    "affiliation":"Department of Physics, College of Arts and Sciences, University of Miami"
                },
                {
                    "container_type":"Author",
                    "filled":[

                    ],
                    "scholar_id":"zOFDJjkAAAAJ",
                    "source":{
                        "name":"CO_AUTHORS_LIST"
                    },
                    "name":"jixiong pu",
                    "affiliation":"huaqiao university"
                },
                {
                    "container_type":"Author",
                    "filled":[

                    ],
                    "scholar_id":"qxfYJa4AAAAJ",
                    "source":{
                        "name":"CO_AUTHORS_LIST"
                    },
                    "name":"Xi Chen (Dawn)",
                    "affiliation":"Beckman Institute, University of Illinois at Urbana Champaign"
                },
                {
                    "container_type":"Author",
                    "filled":[

                    ],
                    "scholar_id":"7nKXQR0AAAAJ",
                    "source":{
                        "name":"CO_AUTHORS_LIST"
                    },
                    "name":"David G. Voelz",
                    "affiliation":"Professor of Electrical and Computer Engineering, New Mexico State University"
                },
                {
                    "container_type":"Author",
                    "filled":[

                    ],
                    "scholar_id":"PC-QIOkAAAAJ",
                    "source":{
                        "name":"CO_AUTHORS_LIST"
                    },
                    "name":"Min Yao (\u59da\u65fb)",
                    "affiliation":"Zhejiang International Studies Unviersity"
                },
                {
                    "container_type":"Author",
                    "filled":[

                    ],
                    "scholar_id":"zjYM7uQAAAAJ",
                    "source":{
                        "name":"CO_AUTHORS_LIST"
                    },
                    "name":"Yahong Chen",
                    "affiliation":"School of Physics and Technology, Soochow University"
                },
                {
                    "container_type":"Author",
                    "filled":[

                    ],
                    "scholar_id":"vVYGFQYAAAAJ",
                    "source":{
                        "name":"CO_AUTHORS_LIST"
                    },
                    "name":"Yalong Gu",
                    "affiliation":"Global Science & Technology"
                },
                {
                    "container_type":"Author",
                    "filled":[

                    ],
                    "scholar_id":"AioqiskAAAAJ",
                    "source":{
                        "name":"CO_AUTHORS_LIST"
                    },
                    "name":"Emre Sermutlu",
                    "affiliation":"\u00c7ankaya \u00dcniversitesi"
                },
                {
                    "container_type":"Author",
                    "filled":[

                    ],
                    "scholar_id":"8ai7weYAAAAJ",
                    "source":{
                        "name":"CO_AUTHORS_LIST"
                    },
                    "name":"Celal Zaim \u00c7il",
                    "affiliation":"professor of electronics, empinovas"
                },
                {
                    "container_type":"Author",
                    "filled":[

                    ],
                    "scholar_id":"hbs7R4wAAAAJ",
                    "source":{
                        "name":"CO_AUTHORS_LIST"
                    },
                    "name":"Prof. Cheng-Liang Zhao\uff08\u8d75\u627f\u826f\uff09",
                    "affiliation":"School of Physical Science and Technology, Soochow University"
                },
                {
                    "container_type":"Author",
                    "filled":[

                    ],
                    "scholar_id":"EuQy760AAAAJ",
                    "source":{
                        "name":"CO_AUTHORS_LIST"
                    },
                    "name":"S. M. Hashemi Rafsanjani",
                    "affiliation":"University of Miami"
                },
                {
                    "container_type":"Author",
                    "filled":[

                    ],
                    "scholar_id":"E6j3x-cAAAAJ",
                    "source":{
                        "name":"CO_AUTHORS_LIST"
                    },
                    "name":"yongtao zhang",
                    "affiliation":"Luoyang Normal University"
                },
                {
                    "container_type":"Author",
                    "filled":[

                    ],
                    "scholar_id":"Ck80nzgAAAAJ",
                    "source":{
                        "name":"CO_AUTHORS_LIST"
                    },
                    "name":"Edward A. Watson",
                    "affiliation":"Vista Applied Optics, LLC & University of Dayton"
                }
            ]
        ]
    ]
}