{
    "columns":[
        "scholar_id",
        "name",
        "affiliation",
        "email_domain",
        "url_picture",
        "citedby",
        "interests",
        "citedby5y",
        "hindex",
        "hindex5y",
        "i10index",
        "i10index5y",
        "coauthors"
    ],
    "index":[
        0
    ],
    "data":[
        [
            "Ko-WdFoAAAAJ",
            "Jian Hui (James) Guan",
            "Instructor, Department of Mathematics, UNC at Chapel Hill",
            "@unc.edu",
            "https:\/\/scholar.google.com\/citations?view_op=medium_photo&user=Ko-WdFoAAAAJ",
            1299,
            [
                "Drops",
                "Porous media",
                "Plants",
                "Faraday Waves"
            ],
            1293,
            6,
            6,
            5,
            5,
            [
                {
                    "container_type":"Author",
                    "filled":[

                    ],
                    "scholar_id":"6Vgft4IAAAAJ",
                    "source":{
                        "name":"CO_AUTHORS_LIST"
                    },
                    "name":"Glen McHale",
                    "affiliation":"University of Edinburgh"
                },
                {
                    "container_type":"Author",
                    "filled":[

                    ],
                    "scholar_id":"T_M77NIAAAAJ",
                    "source":{
                        "name":"CO_AUTHORS_LIST"
                    },
                    "name":"Gary George Wells",
                    "affiliation":"Senior Lecturer, Edinburgh University"
                },
                {
                    "container_type":"Author",
                    "filled":[

                    ],
                    "scholar_id":"RG5zFPAAAAAJ",
                    "source":{
                        "name":"CO_AUTHORS_LIST"
                    },
                    "name":"Ben B. Xu",
                    "affiliation":"Northumbria University, University of Massachusetts Amherst, Heriot-Watt University"
                },
                {
                    "container_type":"Author",
                    "filled":[

                    ],
                    "scholar_id":"Jut8z7gAAAAJ",
                    "source":{
                        "name":"CO_AUTHORS_LIST"
                    },
                    "name":"David Wood",
                    "affiliation":"University of Northumbria at Newcastle"
                },
                {
                    "container_type":"Author",
                    "filled":[

                    ],
                    "scholar_id":"rKLDzjEAAAAJ",
                    "source":{
                        "name":"CO_AUTHORS_LIST"
                    },
                    "name":"Nicasio Geraldi",
                    "affiliation":"Technical Specialist - Commercial (Physics and Materials), Nottingham Trent University"
                },
                {
                    "container_type":"Author",
                    "filled":[

                    ],
                    "scholar_id":"yiBhQ5IAAAAJ",
                    "source":{
                        "name":"CO_AUTHORS_LIST"
                    },
                    "name":"Rodrigo Ledesma-Aguilar",
                    "affiliation":"Institute of Multiscale Thermofluids, School of Engineering, University of Edinburgh"
                },
                {
                    "container_type":"Author",
                    "filled":[

                    ],
                    "scholar_id":"dWg62SIAAAAJ",
                    "source":{
                        "name":"CO_AUTHORS_LIST"
                    },
                    "name":"\u00c9lfego Ruiz-Guti\u00e9rrez",
                    "affiliation":"Postdoctoral Research Associate, The University of Edinburgh"
                },
                {
                    "container_type":"Author",
                    "filled":[

                    ],
                    "scholar_id":"faszbxEAAAAJ",
                    "source":{
                        "name":"CO_AUTHORS_LIST"
                    },
                    "name":"Richard Fu (Yongqing Fu \u5085\u6c38\u5e86\uff09",
                    "affiliation":"Professor in Northumbria University, Newcastle, UK"
                },
                {
                    "container_type":"Author",
                    "filled":[

                    ],
                    "scholar_id":"J3TGLoIAAAAJ",
                    "source":{
                        "name":"CO_AUTHORS_LIST"
                    },
                    "name":"Michael Newton",
                    "affiliation":"Nottingham Trent University"
                },
                {
                    "container_type":"Author",
                    "filled":[

                    ],
                    "scholar_id":"LK5Mn2oAAAAJ",
                    "source":{
                        "name":"CO_AUTHORS_LIST"
                    },
                    "name":"Linzi E. Dodd MEng PhD (Dunelm) FH...",
                    "affiliation":"Senior Lecturer, Northumbria University"
                },
                {
                    "container_type":"Author",
                    "filled":[

                    ],
                    "scholar_id":"d_V5c3sAAAAJ",
                    "source":{
                        "name":"CO_AUTHORS_LIST"
                    },
                    "name":"Finn Box",
                    "affiliation":"University of Manchester"
                },
                {
                    "container_type":"Author",
                    "filled":[

                    ],
                    "scholar_id":"RjHL_WIAAAAJ",
                    "source":{
                        "name":"CO_AUTHORS_LIST"
                    },
                    "name":"Chris MacMinn",
                    "affiliation":"University of Oxford"
                },
                {
                    "container_type":"Author",
                    "filled":[

                    ],
                    "scholar_id":"8tPuUEwAAAAJ",
                    "source":{
                        "name":"CO_AUTHORS_LIST"
                    },
                    "name":"Satyajit Pramanik",
                    "affiliation":"Assistant Professor, Indian Institute of Technology Gandhinagar"
                },
                {
                    "container_type":"Author",
                    "filled":[

                    ],
                    "scholar_id":"D51DwqcAAAAJ",
                    "source":{
                        "name":"CO_AUTHORS_LIST"
                    },
                    "name":"Sungyon Lee",
                    "affiliation":"Assistant Professor of Mechanical Engineering, University of Minnesota"
                }
            ]
        ]
    ]
}