{
    "columns":[
        "scholar_id",
        "name",
        "affiliation",
        "email_domain",
        "url_picture",
        "citedby",
        "interests",
        "citedby5y",
        "hindex",
        "hindex5y",
        "i10index",
        "i10index5y",
        "coauthors"
    ],
    "index":[
        0
    ],
    "data":[
        [
            "lIHUeFYAAAAJ",
            "Matthew Y. Sfeir",
            "Photonics Initiative, City University of New York",
            "@gc.cuny.edu",
            "https:\/\/scholar.google.com\/citations?view_op=medium_photo&user=lIHUeFYAAAAJ",
            10029,
            [
                "Nanoscience",
                "Photophysics",
                "Spectroscopy",
                "Light Harvesting"
            ],
            7039,
            44,
            39,
            90,
            83,
            [
                {
                    "container_type":"Author",
                    "filled":[

                    ],
                    "scholar_id":"X8frSD8AAAAJ",
                    "source":{
                        "name":"CO_AUTHORS_LIST"
                    },
                    "name":"Kannatassen Appavoo (Krishen)",
                    "affiliation":"Assistant Professor, Department of Physics, UAB"
                },
                {
                    "container_type":"Author",
                    "filled":[

                    ],
                    "scholar_id":"Lx1MNTsAAAAJ",
                    "source":{
                        "name":"CO_AUTHORS_LIST"
                    },
                    "name":"Luis M. Campos",
                    "affiliation":"Department of Chemistry, Columbia University"
                },
                {
                    "container_type":"Author",
                    "filled":[

                    ],
                    "scholar_id":"_0siAFAAAAAJ",
                    "source":{
                        "name":"CO_AUTHORS_LIST"
                    },
                    "name":"Tony F Heinz",
                    "affiliation":"Dept. of Applied Physics and SLAC National Accelerator Lab, Stanford University"
                },
                {
                    "container_type":"Author",
                    "filled":[

                    ],
                    "scholar_id":"DTjCwucAAAAJ",
                    "source":{
                        "name":"CO_AUTHORS_LIST"
                    },
                    "name":"Sam Sanders",
                    "affiliation":"Harvard - Quadratic3D"
                },
                {
                    "container_type":"Author",
                    "filled":[

                    ],
                    "scholar_id":"GT0oh5QAAAAJ",
                    "source":{
                        "name":"CO_AUTHORS_LIST"
                    },
                    "name":"Louis Brus",
                    "affiliation":"Professor of Chemistry, Columbia University"
                },
                {
                    "container_type":"Author",
                    "filled":[

                    ],
                    "scholar_id":"vveoESoAAAAJ",
                    "source":{
                        "name":"CO_AUTHORS_LIST"
                    },
                    "name":"Rongchao Jin",
                    "affiliation":"Carnegie Mellon University"
                },
                {
                    "container_type":"Author",
                    "filled":[

                    ],
                    "scholar_id":"GfiLZG8AAAAJ",
                    "source":{
                        "name":"CO_AUTHORS_LIST"
                    },
                    "name":"Wanyi Nie",
                    "affiliation":"Los Alamos National Lab"
                },
                {
                    "container_type":"Author",
                    "filled":[

                    ],
                    "scholar_id":"DFlvFy0AAAAJ",
                    "source":{
                        "name":"CO_AUTHORS_LIST"
                    },
                    "name":"Jean-Christophe Blancon",
                    "affiliation":"Rice University"
                },
                {
                    "container_type":"Author",
                    "filled":[

                    ],
                    "scholar_id":"wZSGnjYAAAAJ",
                    "source":{
                        "name":"CO_AUTHORS_LIST"
                    },
                    "name":"Jacky Even",
                    "affiliation":"Professor INSA Rennes, IUF, FOTON Institute, CNRS, France"
                },
                {
                    "container_type":"Author",
                    "filled":[

                    ],
                    "scholar_id":"6FBpjCQAAAAJ",
                    "source":{
                        "name":"CO_AUTHORS_LIST"
                    },
                    "name":"Jianlong Xia",
                    "affiliation":"Professor, Wuhan University of Technology"
                },
                {
                    "container_type":"Author",
                    "filled":[

                    ],
                    "scholar_id":"zZWdEeAAAAAJ",
                    "source":{
                        "name":"CO_AUTHORS_LIST"
                    },
                    "name":"Erik Busby, PhD",
                    "affiliation":"Lawrence Livermore National Laboratory"
                },
                {
                    "container_type":"Author",
                    "filled":[

                    ],
                    "scholar_id":"G7gLHXIAAAAJ",
                    "source":{
                        "name":"CO_AUTHORS_LIST"
                    },
                    "name":"M. Tuan Trinh",
                    "affiliation":"Res. Asst. Professor, University of South Florida"
                },
                {
                    "container_type":"Author",
                    "filled":[

                    ],
                    "scholar_id":"fakKz8sAAAAJ",
                    "source":{
                        "name":"CO_AUTHORS_LIST"
                    },
                    "name":"Qin Wu",
                    "affiliation":"Chemist, Center for Functional Nanomaterials, Brookhaven National Laboratory"
                },
                {
                    "container_type":"Author",
                    "filled":[

                    ],
                    "scholar_id":"J0XQ6I8AAAAJ",
                    "source":{
                        "name":"CO_AUTHORS_LIST"
                    },
                    "name":"Aditya D. Mohite",
                    "affiliation":"Associate Professor of Chemical & Biomolecular Engineering, Rice University"
                }
            ]
        ]
    ]
}